{
  "parent": "bakery:main/root",
  "display": {
    "icon": {
      "item": "bakery:yeast"
    },
    "title": {
      "translate": "advancement.bakery.get_yeast"
    },
    "description": {
      "translate": "advancement.bakery.get_yeast.desc"
    },
    "frame": "task",
    "show_toast": true,
    "announce_to_chat": true,
    "hidden": false
  },
  "rewards": {
    "experience": 10
  },
  "criteria": {
    "get_yeast": {
      "trigger": "minecraft:inventory_changed",
      "conditions": {
        "items": [
          {
            "items": ["bakery:yeast"]
          }
        ]
      }
    }
  },
  "requirements": [
    [
      "get_yeast"
    ]
  ]
}