{
  "parent": "bakery:main/get_yeast",
  "criteria": {
    "brick_stove": {
      "conditions": {
        "location": [
          {
            "block": "bakery:brick_stove",
            "condition": "minecraft:block_state_property"
          }

        ]
      },
      "trigger": "minecraft:placed_block"
    },
    "granite_stove": {
      "conditions": {
        "location": [
          {
            "block": "bakery:granite_stove",
            "condition": "minecraft:block_state_property"
          }

        ]
      },
      "trigger": "minecraft:placed_block"
    },
    "cobblestone_stove": {
      "conditions": {
        "location": [
          {
            "block": "bakery:cobblestone_stove",
            "condition": "minecraft:block_state_property"
          }

        ]
      },
      "trigger": "minecraft:placed_block"
    },
    "stone_bricks_stove": {
      "conditions": {
        "location": [
          {
            "block": "bakery:stone_bricks_stove",
            "condition": "minecraft:block_state_property"
          }

        ]
      },
      "trigger": "minecraft:placed_block"
    },
    "sandstone_stove": {
      "conditions": {
        "location": [
          {
            "block": "bakery:sandstone_stove",
            "condition": "minecraft:block_state_property"
          }

        ]
      },
      "trigger": "minecraft:placed_block"
    },
    "deepslate_stove": {
      "conditions": {
        "location": [
          {
            "block": "bakery:deepslate_stove",
            "condition": "minecraft:block_state_property"
          }

        ]
      },
      "trigger": "minecraft:placed_block"
    },
    "end_stove": {
      "conditions": {
        "location": [
          {
            "block": "bakery:end_stove",
            "condition": "minecraft:block_state_property"
          }

        ]
      },
      "trigger": "minecraft:placed_block"
    },
    "quartz_stove": {
      "conditions": {
        "location": [
          {
            "block": "bakery:quartz_stove",
            "condition": "minecraft:block_state_property"
          }

        ]
      },
      "trigger": "minecraft:placed_block"
    },
    "red_nether_bricks_stove": {
      "conditions": {
        "location": [
          {
            "block": "bakery:red_nether_bricks_stove",
            "condition": "minecraft:block_state_property"
          }

        ]
      },
      "trigger": "minecraft:placed_block"
    }
  },
  "display": {
    "announce_to_chat": true,
    "description": {
      "translate": "advancement.bakery.place_stove.desc"
    },
    "frame": "task",
    "hidden": false,
    "icon": {
      "item": "bakery:brick_stove"
    },
    "show_toast": true,
    "title": {
      "translate": "advancement.bakery.place_stove"
    }
  },
  "requirements": [
    [
      "brick_stove",
      "granite_stove",
      "cobblestone_stove",
      "stone_bricks_stove",
      "sandstone_stove",
      "deepslate_stove",
      "end_stove",
      "quartz_stove",
      "red_nether_bricks_stove"
    ]
  ],
  "sends_telemetry_event": true
}